{
	"artifacts" : 
	[
		{
			"path" : "CMakeFiles/nanogui-obj.dir/./ext/nanovg/src/nanovg.c.o"
		},
		{
			"path" : "CMakeFiles/nanogui-obj.dir/./ext/nanogui/darwin.mm.o"
		},
		{
			"path" : "CMakeFiles/nanogui-obj.dir/./nanogui_resources.cpp.o"
		},
		{
			"path" : "CMakeFiles/nanogui-obj.dir/./ext/nanogui/glutil.cpp.o"
		},
		{
			"path" : "CMakeFiles/nanogui-obj.dir/./ext/nanogui/common.cpp.o"
		},
		{
			"path" : "CMakeFiles/nanogui-obj.dir/./ext/nanogui/widget.cpp.o"
		},
		{
			"path" : "CMakeFiles/nanogui-obj.dir/./ext/nanogui/theme.cpp.o"
		},
		{
			"path" : "CMakeFiles/nanogui-obj.dir/./ext/nanogui/layout.cpp.o"
		},
		{
			"path" : "CMakeFiles/nanogui-obj.dir/./ext/nanogui/screen.cpp.o"
		},
		{
			"path" : "CMakeFiles/nanogui-obj.dir/./ext/nanogui/label.cpp.o"
		},
		{
			"path" : "CMakeFiles/nanogui-obj.dir/./ext/nanogui/window.cpp.o"
		},
		{
			"path" : "CMakeFiles/nanogui-obj.dir/./ext/nanogui/popup.cpp.o"
		},
		{
			"path" : "CMakeFiles/nanogui-obj.dir/./ext/nanogui/checkbox.cpp.o"
		},
		{
			"path" : "CMakeFiles/nanogui-obj.dir/./ext/nanogui/button.cpp.o"
		},
		{
			"path" : "CMakeFiles/nanogui-obj.dir/./ext/nanogui/popupbutton.cpp.o"
		},
		{
			"path" : "CMakeFiles/nanogui-obj.dir/./ext/nanogui/combobox.cpp.o"
		},
		{
			"path" : "CMakeFiles/nanogui-obj.dir/./ext/nanogui/progressbar.cpp.o"
		},
		{
			"path" : "CMakeFiles/nanogui-obj.dir/./ext/nanogui/slider.cpp.o"
		},
		{
			"path" : "CMakeFiles/nanogui-obj.dir/./ext/nanogui/messagedialog.cpp.o"
		},
		{
			"path" : "CMakeFiles/nanogui-obj.dir/./ext/nanogui/textbox.cpp.o"
		},
		{
			"path" : "CMakeFiles/nanogui-obj.dir/./ext/nanogui/imagepanel.cpp.o"
		},
		{
			"path" : "CMakeFiles/nanogui-obj.dir/./ext/nanogui/imageview.cpp.o"
		},
		{
			"path" : "CMakeFiles/nanogui-obj.dir/./ext/nanogui/vscrollpanel.cpp.o"
		},
		{
			"path" : "CMakeFiles/nanogui-obj.dir/./ext/nanogui/colorwheel.cpp.o"
		},
		{
			"path" : "CMakeFiles/nanogui-obj.dir/./ext/nanogui/colorpicker.cpp.o"
		},
		{
			"path" : "CMakeFiles/nanogui-obj.dir/./ext/nanogui/graph.cpp.o"
		},
		{
			"path" : "CMakeFiles/nanogui-obj.dir/./ext/nanogui/stackedwidget.cpp.o"
		},
		{
			"path" : "CMakeFiles/nanogui-obj.dir/./ext/nanogui/tabheader.cpp.o"
		},
		{
			"path" : "CMakeFiles/nanogui-obj.dir/./ext/nanogui/tabwidget.cpp.o"
		},
		{
			"path" : "CMakeFiles/nanogui-obj.dir/./ext/nanogui/glcanvas.cpp.o"
		},
		{
			"path" : "CMakeFiles/nanogui-obj.dir/./ext/nanogui/serializer.cpp.o"
		}
	],
	"backtrace" : 1,
	"backtraceGraph" : 
	{
		"commands" : 
		[
			"add_library",
			"add_compile_options",
			"add_definitions",
			"set_property",
			"include_directories"
		],
		"files" : 
		[
			"CMakeLists.txt"
		],
		"nodes" : 
		[
			{
				"file" : 0
			},
			{
				"command" : 0,
				"file" : 0,
				"line" : 295,
				"parent" : 0
			},
			{
				"command" : 1,
				"file" : 0,
				"line" : 289,
				"parent" : 0
			},
			{
				"command" : 2,
				"file" : 0,
				"line" : 282,
				"parent" : 0
			},
			{
				"command" : 2,
				"file" : 0,
				"line" : 292,
				"parent" : 0
			},
			{
				"command" : 3,
				"file" : 0,
				"line" : 349,
				"parent" : 0
			},
			{
				"command" : 3,
				"file" : 0,
				"line" : 371,
				"parent" : 0
			},
			{
				"command" : 4,
				"file" : 0,
				"line" : 243,
				"parent" : 0
			},
			{
				"command" : 4,
				"file" : 0,
				"line" : 283,
				"parent" : 0
			}
		]
	},
	"compileGroups" : 
	[
		{
			"compileCommandFragments" : 
			[
				{
					"fragment" : " -Wno-deprecated-declarations -g -isysroot /Library/Developer/CommandLineTools/SDKs/MacOSX10.15.sdk -fPIC"
				},
				{
					"backtrace" : 2,
					"fragment" : "-fobjc-arc"
				}
			],
			"defines" : 
			[
				{
					"backtrace" : 3,
					"define" : "CORO_SJLJ"
				},
				{
					"backtrace" : 4,
					"define" : "GLAD_GLAPI_EXPORT"
				},
				{
					"backtrace" : 5,
					"define" : "NANOGUI_BUILD"
				},
				{
					"backtrace" : 4,
					"define" : "NANOGUI_SHARED"
				},
				{
					"backtrace" : 5,
					"define" : "NVG_BUILD"
				},
				{
					"backtrace" : 6,
					"define" : "NVG_SHARED"
				},
				{
					"backtrace" : 6,
					"define" : "_GLFW_BUILD_DLL"
				}
			],
			"includes" : 
			[
				{
					"backtrace" : 7,
					"path" : "/Users/eason/Desktop/HKUST/git/COMP5411_Advanced_CG/ext/eigen"
				},
				{
					"backtrace" : 7,
					"path" : "/Users/eason/Desktop/HKUST/git/COMP5411_Advanced_CG/ext/glfw/include"
				},
				{
					"backtrace" : 7,
					"path" : "/Users/eason/Desktop/HKUST/git/COMP5411_Advanced_CG/ext/nanovg/src"
				},
				{
					"backtrace" : 7,
					"path" : "/Users/eason/Desktop/HKUST/git/COMP5411_Advanced_CG/include"
				},
				{
					"backtrace" : 7,
					"path" : "/Users/eason/Desktop/HKUST/git/COMP5411_Advanced_CG/cmake-build-debug"
				},
				{
					"backtrace" : 8,
					"path" : "/Users/eason/Desktop/HKUST/git/COMP5411_Advanced_CG/ext/coro"
				}
			],
			"language" : "C",
			"sourceIndexes" : 
			[
				0
			]
		},
		{
			"compileCommandFragments" : 
			[
				{
					"fragment" : " -Wall -Wextra -std=c++14 -stdlib=libc++ -g -isysroot /Library/Developer/CommandLineTools/SDKs/MacOSX10.15.sdk -fPIC"
				},
				{
					"backtrace" : 2,
					"fragment" : "-fobjc-arc"
				}
			],
			"defines" : 
			[
				{
					"backtrace" : 3,
					"define" : "CORO_SJLJ"
				},
				{
					"backtrace" : 4,
					"define" : "GLAD_GLAPI_EXPORT"
				},
				{
					"backtrace" : 5,
					"define" : "NANOGUI_BUILD"
				},
				{
					"backtrace" : 4,
					"define" : "NANOGUI_SHARED"
				},
				{
					"backtrace" : 5,
					"define" : "NVG_BUILD"
				},
				{
					"backtrace" : 6,
					"define" : "NVG_SHARED"
				},
				{
					"backtrace" : 6,
					"define" : "_GLFW_BUILD_DLL"
				}
			],
			"includes" : 
			[
				{
					"backtrace" : 7,
					"path" : "/Users/eason/Desktop/HKUST/git/COMP5411_Advanced_CG/ext/eigen"
				},
				{
					"backtrace" : 7,
					"path" : "/Users/eason/Desktop/HKUST/git/COMP5411_Advanced_CG/ext/glfw/include"
				},
				{
					"backtrace" : 7,
					"path" : "/Users/eason/Desktop/HKUST/git/COMP5411_Advanced_CG/ext/nanovg/src"
				},
				{
					"backtrace" : 7,
					"path" : "/Users/eason/Desktop/HKUST/git/COMP5411_Advanced_CG/include"
				},
				{
					"backtrace" : 7,
					"path" : "/Users/eason/Desktop/HKUST/git/COMP5411_Advanced_CG/cmake-build-debug"
				},
				{
					"backtrace" : 8,
					"path" : "/Users/eason/Desktop/HKUST/git/COMP5411_Advanced_CG/ext/coro"
				}
			],
			"language" : "CXX",
			"sourceIndexes" : 
			[
				1,
				2,
				4,
				6,
				8,
				10,
				12,
				14,
				16,
				18,
				20,
				22,
				24,
				26,
				28,
				30,
				32,
				34,
				36,
				38,
				40,
				42,
				44,
				46,
				48,
				50,
				52,
				54,
				56,
				64
			]
		}
	],
	"id" : "nanogui-obj::@6890427a1f51a3e7e1df",
	"name" : "nanogui-obj",
	"paths" : 
	{
		"build" : ".",
		"source" : "."
	},
	"sourceGroups" : 
	[
		{
			"name" : "Source Files",
			"sourceIndexes" : 
			[
				0,
				1,
				2,
				4,
				6,
				8,
				10,
				12,
				14,
				16,
				18,
				20,
				22,
				24,
				26,
				28,
				30,
				32,
				34,
				36,
				38,
				40,
				42,
				44,
				46,
				48,
				50,
				52,
				54,
				56,
				64
			]
		},
		{
			"name" : "Header Files",
			"sourceIndexes" : 
			[
				3,
				5,
				7,
				9,
				11,
				13,
				15,
				17,
				19,
				21,
				23,
				25,
				27,
				29,
				31,
				33,
				35,
				37,
				39,
				41,
				43,
				45,
				47,
				49,
				51,
				53,
				55,
				57,
				58,
				59,
				60,
				61,
				62,
				63
			]
		},
		{
			"name" : "CMake Rules",
			"sourceIndexes" : 
			[
				65
			]
		}
	],
	"sources" : 
	[
		{
			"backtrace" : 1,
			"compileGroupIndex" : 0,
			"path" : "ext/nanovg/src/nanovg.c",
			"sourceGroupIndex" : 0
		},
		{
			"backtrace" : 1,
			"compileGroupIndex" : 1,
			"path" : "ext/nanogui/darwin.mm",
			"sourceGroupIndex" : 0
		},
		{
			"backtrace" : 1,
			"compileGroupIndex" : 1,
			"isGenerated" : true,
			"path" : "cmake-build-debug/nanogui_resources.cpp",
			"sourceGroupIndex" : 0
		},
		{
			"backtrace" : 1,
			"path" : "include/nanogui/glutil.h",
			"sourceGroupIndex" : 1
		},
		{
			"backtrace" : 1,
			"compileGroupIndex" : 1,
			"path" : "ext/nanogui/glutil.cpp",
			"sourceGroupIndex" : 0
		},
		{
			"backtrace" : 1,
			"path" : "include/nanogui/common.h",
			"sourceGroupIndex" : 1
		},
		{
			"backtrace" : 1,
			"compileGroupIndex" : 1,
			"path" : "ext/nanogui/common.cpp",
			"sourceGroupIndex" : 0
		},
		{
			"backtrace" : 1,
			"path" : "include/nanogui/widget.h",
			"sourceGroupIndex" : 1
		},
		{
			"backtrace" : 1,
			"compileGroupIndex" : 1,
			"path" : "ext/nanogui/widget.cpp",
			"sourceGroupIndex" : 0
		},
		{
			"backtrace" : 1,
			"path" : "include/nanogui/theme.h",
			"sourceGroupIndex" : 1
		},
		{
			"backtrace" : 1,
			"compileGroupIndex" : 1,
			"path" : "ext/nanogui/theme.cpp",
			"sourceGroupIndex" : 0
		},
		{
			"backtrace" : 1,
			"path" : "include/nanogui/layout.h",
			"sourceGroupIndex" : 1
		},
		{
			"backtrace" : 1,
			"compileGroupIndex" : 1,
			"path" : "ext/nanogui/layout.cpp",
			"sourceGroupIndex" : 0
		},
		{
			"backtrace" : 1,
			"path" : "include/nanogui/screen.h",
			"sourceGroupIndex" : 1
		},
		{
			"backtrace" : 1,
			"compileGroupIndex" : 1,
			"path" : "ext/nanogui/screen.cpp",
			"sourceGroupIndex" : 0
		},
		{
			"backtrace" : 1,
			"path" : "include/nanogui/label.h",
			"sourceGroupIndex" : 1
		},
		{
			"backtrace" : 1,
			"compileGroupIndex" : 1,
			"path" : "ext/nanogui/label.cpp",
			"sourceGroupIndex" : 0
		},
		{
			"backtrace" : 1,
			"path" : "include/nanogui/window.h",
			"sourceGroupIndex" : 1
		},
		{
			"backtrace" : 1,
			"compileGroupIndex" : 1,
			"path" : "ext/nanogui/window.cpp",
			"sourceGroupIndex" : 0
		},
		{
			"backtrace" : 1,
			"path" : "include/nanogui/popup.h",
			"sourceGroupIndex" : 1
		},
		{
			"backtrace" : 1,
			"compileGroupIndex" : 1,
			"path" : "ext/nanogui/popup.cpp",
			"sourceGroupIndex" : 0
		},
		{
			"backtrace" : 1,
			"path" : "include/nanogui/checkbox.h",
			"sourceGroupIndex" : 1
		},
		{
			"backtrace" : 1,
			"compileGroupIndex" : 1,
			"path" : "ext/nanogui/checkbox.cpp",
			"sourceGroupIndex" : 0
		},
		{
			"backtrace" : 1,
			"path" : "include/nanogui/button.h",
			"sourceGroupIndex" : 1
		},
		{
			"backtrace" : 1,
			"compileGroupIndex" : 1,
			"path" : "ext/nanogui/button.cpp",
			"sourceGroupIndex" : 0
		},
		{
			"backtrace" : 1,
			"path" : "include/nanogui/popupbutton.h",
			"sourceGroupIndex" : 1
		},
		{
			"backtrace" : 1,
			"compileGroupIndex" : 1,
			"path" : "ext/nanogui/popupbutton.cpp",
			"sourceGroupIndex" : 0
		},
		{
			"backtrace" : 1,
			"path" : "include/nanogui/combobox.h",
			"sourceGroupIndex" : 1
		},
		{
			"backtrace" : 1,
			"compileGroupIndex" : 1,
			"path" : "ext/nanogui/combobox.cpp",
			"sourceGroupIndex" : 0
		},
		{
			"backtrace" : 1,
			"path" : "include/nanogui/progressbar.h",
			"sourceGroupIndex" : 1
		},
		{
			"backtrace" : 1,
			"compileGroupIndex" : 1,
			"path" : "ext/nanogui/progressbar.cpp",
			"sourceGroupIndex" : 0
		},
		{
			"backtrace" : 1,
			"path" : "include/nanogui/slider.h",
			"sourceGroupIndex" : 1
		},
		{
			"backtrace" : 1,
			"compileGroupIndex" : 1,
			"path" : "ext/nanogui/slider.cpp",
			"sourceGroupIndex" : 0
		},
		{
			"backtrace" : 1,
			"path" : "include/nanogui/messagedialog.h",
			"sourceGroupIndex" : 1
		},
		{
			"backtrace" : 1,
			"compileGroupIndex" : 1,
			"path" : "ext/nanogui/messagedialog.cpp",
			"sourceGroupIndex" : 0
		},
		{
			"backtrace" : 1,
			"path" : "include/nanogui/textbox.h",
			"sourceGroupIndex" : 1
		},
		{
			"backtrace" : 1,
			"compileGroupIndex" : 1,
			"path" : "ext/nanogui/textbox.cpp",
			"sourceGroupIndex" : 0
		},
		{
			"backtrace" : 1,
			"path" : "include/nanogui/imagepanel.h",
			"sourceGroupIndex" : 1
		},
		{
			"backtrace" : 1,
			"compileGroupIndex" : 1,
			"path" : "ext/nanogui/imagepanel.cpp",
			"sourceGroupIndex" : 0
		},
		{
			"backtrace" : 1,
			"path" : "include/nanogui/imageview.h",
			"sourceGroupIndex" : 1
		},
		{
			"backtrace" : 1,
			"compileGroupIndex" : 1,
			"path" : "ext/nanogui/imageview.cpp",
			"sourceGroupIndex" : 0
		},
		{
			"backtrace" : 1,
			"path" : "include/nanogui/vscrollpanel.h",
			"sourceGroupIndex" : 1
		},
		{
			"backtrace" : 1,
			"compileGroupIndex" : 1,
			"path" : "ext/nanogui/vscrollpanel.cpp",
			"sourceGroupIndex" : 0
		},
		{
			"backtrace" : 1,
			"path" : "include/nanogui/colorwheel.h",
			"sourceGroupIndex" : 1
		},
		{
			"backtrace" : 1,
			"compileGroupIndex" : 1,
			"path" : "ext/nanogui/colorwheel.cpp",
			"sourceGroupIndex" : 0
		},
		{
			"backtrace" : 1,
			"path" : "include/nanogui/colorpicker.h",
			"sourceGroupIndex" : 1
		},
		{
			"backtrace" : 1,
			"compileGroupIndex" : 1,
			"path" : "ext/nanogui/colorpicker.cpp",
			"sourceGroupIndex" : 0
		},
		{
			"backtrace" : 1,
			"path" : "include/nanogui/graph.h",
			"sourceGroupIndex" : 1
		},
		{
			"backtrace" : 1,
			"compileGroupIndex" : 1,
			"path" : "ext/nanogui/graph.cpp",
			"sourceGroupIndex" : 0
		},
		{
			"backtrace" : 1,
			"path" : "include/nanogui/stackedwidget.h",
			"sourceGroupIndex" : 1
		},
		{
			"backtrace" : 1,
			"compileGroupIndex" : 1,
			"path" : "ext/nanogui/stackedwidget.cpp",
			"sourceGroupIndex" : 0
		},
		{
			"backtrace" : 1,
			"path" : "include/nanogui/tabheader.h",
			"sourceGroupIndex" : 1
		},
		{
			"backtrace" : 1,
			"compileGroupIndex" : 1,
			"path" : "ext/nanogui/tabheader.cpp",
			"sourceGroupIndex" : 0
		},
		{
			"backtrace" : 1,
			"path" : "include/nanogui/tabwidget.h",
			"sourceGroupIndex" : 1
		},
		{
			"backtrace" : 1,
			"compileGroupIndex" : 1,
			"path" : "ext/nanogui/tabwidget.cpp",
			"sourceGroupIndex" : 0
		},
		{
			"backtrace" : 1,
			"path" : "include/nanogui/glcanvas.h",
			"sourceGroupIndex" : 1
		},
		{
			"backtrace" : 1,
			"compileGroupIndex" : 1,
			"path" : "ext/nanogui/glcanvas.cpp",
			"sourceGroupIndex" : 0
		},
		{
			"backtrace" : 1,
			"path" : "include/nanogui/formhelper.h",
			"sourceGroupIndex" : 1
		},
		{
			"backtrace" : 1,
			"path" : "include/nanogui/toolbutton.h",
			"sourceGroupIndex" : 1
		},
		{
			"backtrace" : 1,
			"path" : "include/nanogui/opengl.h",
			"sourceGroupIndex" : 1
		},
		{
			"backtrace" : 1,
			"path" : "include/nanogui/nanogui.h",
			"sourceGroupIndex" : 1
		},
		{
			"backtrace" : 1,
			"path" : "include/nanogui/serializer/core.h",
			"sourceGroupIndex" : 1
		},
		{
			"backtrace" : 1,
			"path" : "include/nanogui/serializer/opengl.h",
			"sourceGroupIndex" : 1
		},
		{
			"backtrace" : 1,
			"path" : "include/nanogui/serializer/sparse.h",
			"sourceGroupIndex" : 1
		},
		{
			"backtrace" : 1,
			"compileGroupIndex" : 1,
			"path" : "ext/nanogui/serializer.cpp",
			"sourceGroupIndex" : 0
		},
		{
			"backtrace" : 0,
			"isGenerated" : true,
			"path" : "cmake-build-debug/nanogui_resources.cpp.rule",
			"sourceGroupIndex" : 2
		}
	],
	"type" : "OBJECT_LIBRARY"
}
